stardust/__init__.py
stardust/cli.py
stardust/file_handler.py
stardust/py.typed
stardust/stardust.py
stardust-0.0.7.dist-info/METADATA
stardust-0.0.7.dist-info/WHEEL
stardust-0.0.7.dist-info/entry_points.txt
stardust-0.0.7.dist-info/licenses/LICENSE.txt
stardust-0.0.7.dist-info/RECORD
