Metadata-Version: 2.3
Name: stardust
Version: 0.0.7
Summary: Stardust is micro web framework inspired by serverless and lambda deployments.
Project-URL: Repository, https://github.com/lukefx/stardust
Author-email: Luca Simone <info@lucasimone.info>
License: MIT
License-File: LICENSE.txt
Keywords: framework,lambda,serverless,web
Classifier: Development Status :: 4 - Beta
Classifier: Intended Audience :: Developers
Classifier: Programming Language :: Python :: 3
Classifier: Programming Language :: Python :: 3.10
Classifier: Programming Language :: Python :: 3.11
Classifier: Programming Language :: Python :: 3.12
Classifier: Programming Language :: Python :: 3.13
Classifier: Topic :: Internet :: WWW/HTTP :: HTTP Servers
Classifier: Topic :: Software Development :: Libraries :: Application Frameworks
Requires-Python: >=3.10
Requires-Dist: starlette<0.42.0,>=0.41.2
Requires-Dist: uvicorn<0.33.0,>=0.32.0
